parallel_principal_feature_analysis/__init__.py
parallel_principal_feature_analysis/execute_PFA.py
parallel_principal_feature_analysis/find_relevant_principal_features.py
parallel_principal_feature_analysis/get_mutual_information.py
parallel_principal_feature_analysis/principal_feature_analysis.py
parallel_principal_feature_analysis-1.0.5.dist-info/LICENSE
parallel_principal_feature_analysis-1.0.5.dist-info/METADATA
parallel_principal_feature_analysis-1.0.5.dist-info/WHEEL
parallel_principal_feature_analysis-1.0.5.dist-info/top_level.txt
parallel_principal_feature_analysis-1.0.5.dist-info/RECORD
