Metadata-Version: 2.1
Name: parallel-principal-feature-analysis
Version: 1.0.5
Summary: The first package for (parallel) Principal Feature Analysis
Author: Tim Breitenbach & Lauritz Rasbach
Author-email: tim.breitenbach@mathematik.uni-wuerzburg.de, rasbachlauritz@googlemail.com
Classifier: Programming Language :: Python :: 3
Classifier: License :: OSI Approved :: BSD License
Classifier: Operating System :: OS Independent
Requires-Python: >=3.6
License-File: LICENSE
Requires-Dist: numpy
Requires-Dist: scipy
Requires-Dist: pandas
Requires-Dist: networkx
